kkcoffea/__init__.py
kkcoffea/processors.py
kkcoffea/samples.py
kkconfig/__init__.py
kkconfig/local.py
kkdata/__init__.py
kkdata/dm.py
kkplot/__init__.py
KKHEP-0.1.0.dist-info/METADATA
KKHEP-0.1.0.dist-info/WHEEL
KKHEP-0.1.0.dist-info/top_level.txt
KKHEP-0.1.0.dist-info/RECORD
