Metadata-Version: 2.1
Name: KKHEP
Version: 0.1.0
Summary: Collection of helpful tools to make plots for High Energy Physics.
Home-page: https://github.com/kkrizka/KKHEP
Author: Karol Krizka
Author-email: kkrizka@gmail.com
License: UNKNOWN
Platform: UNKNOWN
Classifier: Programming Language :: Python :: 3
Classifier: License :: OSI Approved :: GNU General Public License v3 (GPLv3)
Classifier: Operating System :: OS Independent
Requires-Dist: coffea
Requires-Dist: pyyaml
